axon_projection/__init__.py
axon_projection/axonal_projections.py
axon_projection/check_atlas.py
axon_projection/choose_hierarchy_level.py
axon_projection/classify_axons.py
axon_projection/cli.py
axon_projection/compute_morphometrics.py
axon_projection/config_a_p.cfg
axon_projection/count_tufts.py
axon_projection/plot_results.py
axon_projection/plot_utils.py
axon_projection/prod-forge-nexus.yml
axon_projection/query_atlas.py
axon_projection/run.py
axon_projection/sample_axon.py
axon_projection/separate_tufts.py
axon_projection/version.py
axon_projection/visualize_connections.py
axon_projection/figures_scripts/README.md
axon_projection/figures_scripts/acronyms_to_names.py
axon_projection/figures_scripts/build_connectome.py
axon_projection/figures_scripts/compute_scores.py
axon_projection/figures_scripts/plot_feat_cmp.py
axon_projection/figures_scripts/plot_flatmap_h5/background.png
axon_projection/figures_scripts/plot_flatmap_h5/flatmap_util.py
axon_projection/figures_scripts/plot_flatmap_h5/flatplot.py
axon_projection/figures_scripts/plot_flatmap_h5/parse_cmap.py
axon_projection/figures_scripts/plot_flatmap_h5/plot_multiple_morphs.py
axon_projection/validation/config_synth_favored_new_atlas.cfg
axon_projection/validation/circuit-build/add_axons.py
axon_projection/validation/circuit-build/axon_synth.sh
axon_projection/validation/circuit-build/change_morph_extension.py
axon_projection/validation/circuit-build/post_proc_axon_synth.sh
axon_projection/validation/circuit-build/prepare_axon_synth.sh
axon_projection/validation/circuit-build/lite_template/complete_circuit.sh
axon_projection/validation/circuit-build/lite_template/inputs.sh
axon_projection/validation/circuit-build/lite_template/post_proc_axons.sh
axon_projection/validation/circuit-build/lite_template/prepare_axons.sh
axon_projection/validation/circuit-build/lite_template/synth_axons.sh
axon_projection/validation/circuit-build/lite_template/synth_cells.sh
axon_projection-0.1.1.dist-info/AUTHORS.md
axon_projection-0.1.1.dist-info/LICENSE.txt
axon_projection-0.1.1.dist-info/METADATA
axon_projection-0.1.1.dist-info/WHEEL
axon_projection-0.1.1.dist-info/entry_points.txt
axon_projection-0.1.1.dist-info/top_level.txt
axon_projection-0.1.1.dist-info/RECORD
