Metadata-Version: 2.1
Name: axon-projection
Version: 0.1.1
Summary: A code that analyses long-range axons provided as input, and classify them based on the brain regions they project to.
Home-page: https://axon-projection.readthedocs.io
Author: Blue Brain Project, EPFL
License: Apache License 2.0
Project-URL: Tracker, https://github.com/BlueBrain/axon-projection/issues
Project-URL: Source, https://github.com/BlueBrain/axon-projection
Classifier: Development Status :: 2 - Pre-Alpha
Classifier: Intended Audience :: Education
Classifier: Intended Audience :: Science/Research
Classifier: Programming Language :: Python
Classifier: Programming Language :: Python :: 3
Classifier: Programming Language :: Python :: 3.10
Classifier: Programming Language :: Python :: 3.11
Classifier: Programming Language :: Python :: 3.12
Classifier: Topic :: Scientific/Engineering :: Bio-Informatics
Requires-Python: >=3.9
License-File: LICENSE.txt
License-File: AUTHORS.md
Requires-Dist: axon-synthesis >=0.1.5
Requires-Dist: click >=8
Requires-Dist: matplotlib >=3.9.0
Requires-Dist: networkx >=3.1
Requires-Dist: neurom >=3.2.11
Requires-Dist: nexusforge >=0.8.1
Requires-Dist: numpy >=1.26.4
Requires-Dist: pandas >=1.5
Requires-Dist: plotly >=5.17.0
Requires-Dist: plotly-helper >=0.0.8
Requires-Dist: pycirclize >=1.6.0
Requires-Dist: scikit-learn >=1.3.0
Requires-Dist: tabulate >=0.9.0
Requires-Dist: voxcell >=3.1.9
Provides-Extra: docs
Requires-Dist: docutils <0.21 ; extra == 'docs'
Requires-Dist: m2r2 ; extra == 'docs'
Requires-Dist: sphinx ; extra == 'docs'
Requires-Dist: sphinx-bluebrain-theme ; extra == 'docs'
Requires-Dist: sphinx-click ; extra == 'docs'
Provides-Extra: test
Requires-Dist: mock >=3 ; extra == 'test'
Requires-Dist: pytest >=8.3 ; extra == 'test'
Requires-Dist: pytest-click >=1.1 ; extra == 'test'
Requires-Dist: pytest-console-scripts >=1.4 ; extra == 'test'
Requires-Dist: pytest-cov >=5.0 ; extra == 'test'
Requires-Dist: pytest-html >=4.1 ; extra == 'test'
